<annotation>
	<folder>bnum</folder>
	<filename>bnum_0181.jpg</filename>
	<path>C:\Users\이세정\Desktop\data\bnum\bnum_0181.jpg</path>
	<source>
		<database>Unknown</database>
	</source>
	<size>
		<width>338</width>
		<height>450</height>
		<depth>3</depth>
	</size>
	<segmented>0</segmented>
	<object>
		<name>bnum</name>
		<pose>Unspecified</pose>
		<truncated>0</truncated>
		<difficult>0</difficult>
		<bndbox>
			<xmin>152</xmin>
			<ymin>151</ymin>
			<xmax>209</xmax>
			<ymax>185</ymax>
		</bndbox>
	</object>
</annotation>
